ecl_mcp_server/__init__.py
ecl_mcp_server/__main__.py
ecl_mcp_server/attr.py
ecl_mcp_server/constants.py
ecl_mcp_server/context.py
ecl_mcp_server/core.py
ecl_mcp_server/dev.py
ecl_mcp_server/i18n.py
ecl_mcp_server/models.py
ecl_mcp_server/openapi_signature.py
ecl_mcp_server/pool.py
ecl_mcp_server/singleton.py
ecl_mcp_server/utils.py
ecl_mcp_server/thirdparty/__init__.py
ecl_mcp_server/thirdparty/_secret.py
ecl_mcp_server/tools/__init__.py
ecl_mcp_server/tools/alarm.py
ecl_mcp_server/tools/dashboard.py
ecl_mcp_server/tools/default.py
ecl_mcp_server/tools/etl.py
ecl_mcp_server/tools/group.py
ecl_mcp_server/tools/theme.py
ecl_mcp_server/locales/zh_CN/LC_MESSAGES/messages.mo
ecl_mcp_server-0.1.5.dist-info/METADATA
ecl_mcp_server-0.1.5.dist-info/WHEEL
ecl_mcp_server-0.1.5.dist-info/entry_points.txt
ecl_mcp_server-0.1.5.dist-info/licenses/LICENSE
ecl_mcp_server-0.1.5.dist-info/licenses/licenses/Authlib.txt
ecl_mcp_server-0.1.5.dist-info/licenses/licenses/Pygments.txt
ecl_mcp_server-0.1.5.dist-info/licenses/licenses/annotated-types.txt
ecl_mcp_server-0.1.5.dist-info/licenses/licenses/anyio.txt
ecl_mcp_server-0.1.5.dist-info/licenses/licenses/certifi.txt
ecl_mcp_server-0.1.5.dist-info/licenses/licenses/cffi.txt
ecl_mcp_server-0.1.5.dist-info/licenses/licenses/click.txt
ecl_mcp_server-0.1.5.dist-info/licenses/licenses/cryptography.txt
ecl_mcp_server-0.1.5.dist-info/licenses/licenses/exceptiongroup.txt
ecl_mcp_server-0.1.5.dist-info/licenses/licenses/fastmcp.txt
ecl_mcp_server-0.1.5.dist-info/licenses/licenses/h11.txt
ecl_mcp_server-0.1.5.dist-info/licenses/licenses/httpcore.txt
ecl_mcp_server-0.1.5.dist-info/licenses/licenses/httpx-sse.txt
ecl_mcp_server-0.1.5.dist-info/licenses/licenses/httpx.txt
ecl_mcp_server-0.1.5.dist-info/licenses/licenses/idna.txt
ecl_mcp_server-0.1.5.dist-info/licenses/licenses/markdown-it-py.txt
ecl_mcp_server-0.1.5.dist-info/licenses/licenses/mcp.txt
ecl_mcp_server-0.1.5.dist-info/licenses/licenses/mdurl.txt
ecl_mcp_server-0.1.5.dist-info/licenses/licenses/openapi-pydantic.txt
ecl_mcp_server-0.1.5.dist-info/licenses/licenses/pycparser.txt
ecl_mcp_server-0.1.5.dist-info/licenses/licenses/pydantic-settings.txt
ecl_mcp_server-0.1.5.dist-info/licenses/licenses/pydantic.txt
ecl_mcp_server-0.1.5.dist-info/licenses/licenses/pydantic_core.txt
ecl_mcp_server-0.1.5.dist-info/licenses/licenses/python-dateutil.txt
ecl_mcp_server-0.1.5.dist-info/licenses/licenses/python-dotenv.txt
ecl_mcp_server-0.1.5.dist-info/licenses/licenses/python-multipart.txt
ecl_mcp_server-0.1.5.dist-info/licenses/licenses/pytz.txt
ecl_mcp_server-0.1.5.dist-info/licenses/licenses/rich.txt
ecl_mcp_server-0.1.5.dist-info/licenses/licenses/shellingham.txt
ecl_mcp_server-0.1.5.dist-info/licenses/licenses/six.txt
ecl_mcp_server-0.1.5.dist-info/licenses/licenses/sniffio.txt
ecl_mcp_server-0.1.5.dist-info/licenses/licenses/sse-starlette.txt
ecl_mcp_server-0.1.5.dist-info/licenses/licenses/starlette.txt
ecl_mcp_server-0.1.5.dist-info/licenses/licenses/tabulate.txt
ecl_mcp_server-0.1.5.dist-info/licenses/licenses/typer.txt
ecl_mcp_server-0.1.5.dist-info/licenses/licenses/typing-inspection.txt
ecl_mcp_server-0.1.5.dist-info/licenses/licenses/uvicorn.txt
ecl_mcp_server-0.1.5.dist-info/RECORD
