Metadata-Version: 2.4
Name: ecl-mcp-server
Version: 0.1.5
Summary: A Model Context Protocol server providing tools to access ECL(Elastic Cloud Log) for usage by LLMs
Project-URL: Documentation, https://ecloud.10086.cn/op-help-center/doc/article/93509
License: Apache-2.0
License-File: LICENSE
License-File: licenses/Authlib.txt
License-File: licenses/Pygments.txt
License-File: licenses/annotated-types.txt
License-File: licenses/anyio.txt
License-File: licenses/certifi.txt
License-File: licenses/cffi.txt
License-File: licenses/click.txt
License-File: licenses/cryptography.txt
License-File: licenses/exceptiongroup.txt
License-File: licenses/fastmcp.txt
License-File: licenses/h11.txt
License-File: licenses/httpcore.txt
License-File: licenses/httpx-sse.txt
License-File: licenses/httpx.txt
License-File: licenses/idna.txt
License-File: licenses/markdown-it-py.txt
License-File: licenses/mcp.txt
License-File: licenses/mdurl.txt
License-File: licenses/openapi-pydantic.txt
License-File: licenses/pycparser.txt
License-File: licenses/pydantic-settings.txt
License-File: licenses/pydantic.txt
License-File: licenses/pydantic_core.txt
License-File: licenses/python-dateutil.txt
License-File: licenses/python-dotenv.txt
License-File: licenses/python-multipart.txt
License-File: licenses/pytz.txt
License-File: licenses/rich.txt
License-File: licenses/shellingham.txt
License-File: licenses/six.txt
License-File: licenses/sniffio.txt
License-File: licenses/sse-starlette.txt
License-File: licenses/starlette.txt
License-File: licenses/tabulate.txt
License-File: licenses/typer.txt
License-File: licenses/typing-inspection.txt
License-File: licenses/uvicorn.txt
Keywords: 10086.cn,ECL,journal,llm,mcp
Classifier: Development Status :: 4 - Beta
Classifier: License :: OSI Approved :: Apache Software License
Classifier: Programming Language :: Python
Classifier: Programming Language :: Python :: 3.10
Classifier: Programming Language :: Python :: 3.11
Classifier: Programming Language :: Python :: 3.12
Requires-Python: >=3.10
Requires-Dist: fastmcp>=2.7.0
Requires-Dist: mcp>=1.9.2
Requires-Dist: pydantic>=2.11.5
Requires-Dist: python-dateutil>=2.9.0.post0
Requires-Dist: pytz>=2025.2
Requires-Dist: tabulate>=0.9.0
Requires-Dist: typer>=0.16.0
